access_tastypie/__init__.py
access_tastypie/authorization.py
access_tastypie/resources.py
django_access_tastypie-0.1.0b2.dist-info/LICENSE
django_access_tastypie-0.1.0b2.dist-info/METADATA
django_access_tastypie-0.1.0b2.dist-info/WHEEL
django_access_tastypie-0.1.0b2.dist-info/top_level.txt
django_access_tastypie-0.1.0b2.dist-info/RECORD
